typewriter.py
typewriter2-1.0.0.dist-info/METADATA
typewriter2-1.0.0.dist-info/WHEEL
typewriter2-1.0.0.dist-info/entry_points.txt
typewriter2-1.0.0.dist-info/top_level.txt
typewriter2-1.0.0.dist-info/RECORD
