Metadata-Version: 2.1
Name: typewriter2
Version: 1.0.0
Summary: A library for printing messages with typewriter effects.
Classifier: Programming Language :: Python :: 3
Classifier: License :: OSI Approved :: MIT License
Classifier: Operating System :: OS Independent
